area/__init__.py
area/area.py
area_jot-0.0.1.dist-info/METADATA
area_jot-0.0.1.dist-info/WHEEL
area_jot-0.0.1.dist-info/top_level.txt
area_jot-0.0.1.dist-info/RECORD
