Metadata-Version: 2.4
Name: area-jot
Version: 0.0.1
Summary: A simple Python library to calculate areas
Author: Jot
License: MIT
